graphRL/__init__.py
graphRL/envs/__init__.py
graphRL/envs/graphRL.py
graphRL-0.0.1.dist-info/LICENSE
graphRL-0.0.1.dist-info/METADATA
graphRL-0.0.1.dist-info/WHEEL
graphRL-0.0.1.dist-info/top_level.txt
graphRL-0.0.1.dist-info/RECORD
